thingspro/__init__.py
thingspro/edge/__init__.py
thingspro/edge/api_v1/__init__.py
thingspro/edge/api_v1/api.py
thingspro/edge/func_v1/__init__.py
thingspro/edge/func_v1/datadriven.py
thingspro/edge/func_v1/package.py
thingspro/edge/http_v1/__init__.py
thingspro/edge/http_v1/http.py
thingspro/edge/http_v1/rpc/reverseproxy_pb2.py
thingspro/edge/http_v1/rpc/reverseproxy_pb2_grpc.py
thingspro/edge/tag_v1/__init__.py
thingspro/edge/tag_v1/tag.py
tpfunc-1.2.6.dist-info/LICENSE
tpfunc-1.2.6.dist-info/METADATA
tpfunc-1.2.6.dist-info/WHEEL
tpfunc-1.2.6.dist-info/top_level.txt
tpfunc-1.2.6.dist-info/RECORD
