Metadata-Version: 2.1
Name: tpfunc
Version: 1.2.6
Summary: ThingsPro Edge Function SDK
Home-page: https://github.com/MOXA-ISD/edge-thingspro-function
Author: Justin Tung
Author-email: justincp.tung@moxa.com
License: UNKNOWN
Platform: UNKNOWN
Classifier: Programming Language :: Python :: 3
Classifier: License :: OSI Approved :: MIT License
Classifier: Operating System :: OS Independent
Requires-Python: >=3.9
Requires-Dist: grpcio
Requires-Dist: requests
Requires-Dist: protobuf
